vmbpy/__init__.py
vmbpy/camera.py
vmbpy/error.py
vmbpy/feature.py
vmbpy/featurecontainer.py
vmbpy/frame.py
vmbpy/interface.py
vmbpy/localdevice.py
vmbpy/shared.py
vmbpy/stream.py
vmbpy/transportlayer.py
vmbpy/vmbsystem.py
vmbpy/c_binding/__init__.py
vmbpy/c_binding/vmb_c.py
vmbpy/c_binding/vmb_common.py
vmbpy/c_binding/vmb_image_transform.py
vmbpy/c_binding/wrapped_types.py
vmbpy/util/__init__.py
vmbpy/util/context_decorator.py
vmbpy/util/log.py
vmbpy/util/runtime_type_check.py
vmbpy/util/scoped_log.py
vmbpy/util/tracer.py
vmbpy/util/vmb_enum.py
drd_vmbpy-1.0.4.dist-info/LICENSE.txt
drd_vmbpy-1.0.4.dist-info/METADATA
drd_vmbpy-1.0.4.dist-info/WHEEL
drd_vmbpy-1.0.4.dist-info/top_level.txt
drd_vmbpy-1.0.4.dist-info/RECORD
